architech/__init__.py
architech/build.py
architech-1.0.0.dist-info/LICENSE
architech-1.0.0.dist-info/METADATA
architech-1.0.0.dist-info/WHEEL
architech-1.0.0.dist-info/top_level.txt
architech-1.0.0.dist-info/RECORD
